{"0": "App Mobile", "1": "Scanner", "2": "Nextcloud Sync", "3": "Graph", "4": "Pkms Registry", "5": "Knowledge Screen", "6": "Search Index", "7": "", "8": "Vault", "9": "Models", "10": "Vault Registry", "11": "My Application", "12": "Open File Mac.Podspec", "13": "File Picker.Podspec", "14": "Typst Flutter.Podspec", "15": "Nextcloud Sync Test", "16": "App Mobile", "17": "None", "18": "None", "19": "Manifest", "20": "App Web", "21": "Pods-Runner-Frameworks", "22": "Generatedpluginregistrant", "23": "None", "24": "None", "25": "None", "26": "Mainactivity", "27": "None", "28": "None", "29": "Flutter Export Environment", "30": "Build.Gradle", "31": "Build.Gradle", "32": "Settings.Gradle", "33": "None"}